urm/__init__.py
urm/urm_simulation.py
urm/gui/__init__.py
urm/gui/aliased_group.py
urm/gui/cli.py
urm/gui/load_programs.py
urm/gui/server.py
urm/gui/urm_dec.py
urm/gui/programs/Add.json
urm/gui/programs/Fibb.json
urm/gui/programs/GreaterThan.json
urm/gui/programs/Minus.json
urm/gui/programs/Mul.json
urm/gui/programs/Pred.json
urm/gui/urm-visualization/build_latest/asset-manifest.json
urm/gui/urm-visualization/build_latest/favicon.ico
urm/gui/urm-visualization/build_latest/index.html
urm/gui/urm-visualization/build_latest/logo192.png
urm/gui/urm-visualization/build_latest/logo512.png
urm/gui/urm-visualization/build_latest/manifest.json
urm/gui/urm-visualization/build_latest/robots.txt
urm/gui/urm-visualization/build_latest/static/css/main.fe7904f6.css
urm/gui/urm-visualization/build_latest/static/css/main.fe7904f6.css.map
urm/gui/urm-visualization/build_latest/static/js/453.5907e7e1.chunk.js
urm/gui/urm-visualization/build_latest/static/js/453.5907e7e1.chunk.js.map
urm/gui/urm-visualization/build_latest/static/js/main.043289ef.js
urm/gui/urm-visualization/build_latest/static/js/main.043289ef.js.LICENSE.txt
urm/gui/urm-visualization/build_latest/static/js/main.043289ef.js.map
urm-1.1.0.dist-info/LICENSE
urm-1.1.0.dist-info/METADATA
urm-1.1.0.dist-info/WHEEL
urm-1.1.0.dist-info/entry_points.txt
urm-1.1.0.dist-info/top_level.txt
urm-1.1.0.dist-info/RECORD
