Metadata-Version: 2.1
Name: urm
Version: 1.1.0
Summary: Unlimited Register Machine (URM) Simulator
Home-page: https://github.com/tunmx/URMSimulator
Author: Jingyu Yan
Author-email: tunmxy@163.com
Classifier: Programming Language :: Python :: 3
Classifier: License :: OSI Approved :: MIT License
Classifier: Operating System :: OS Independent
Requires-Python: >=3.7
License-File: LICENSE
Requires-Dist: fastapi
Requires-Dist: uvicorn
Requires-Dist: click
